netbox_k8s_manager/__init__.py
netbox_k8s_manager/filtersets.py
netbox_k8s_manager/navigation.py
netbox_k8s_manager/tables.py
netbox_k8s_manager/urls.py
netbox_k8s_manager/api/__init__.py
netbox_k8s_manager/api/serializers.py
netbox_k8s_manager/api/urls.py
netbox_k8s_manager/api/views.py
netbox_k8s_manager/forms/__init__.py
netbox_k8s_manager/forms/k8s_cluster.py
netbox_k8s_manager/forms/k8s_cluster_type.py
netbox_k8s_manager/forms/k8s_service.py
netbox_k8s_manager/migrations/0001_initial.py
netbox_k8s_manager/migrations/__init__.py
netbox_k8s_manager/models/__init__.py
netbox_k8s_manager/models/k8s_cluster.py
netbox_k8s_manager/models/k8s_cluster_type.py
netbox_k8s_manager/models/k8s_service.py
netbox_k8s_manager/templates/netbox_k8s_manager/k8scluster.html
netbox_k8s_manager/templates/netbox_k8s_manager/k8sclustertype.html
netbox_k8s_manager/templates/netbox_k8s_manager/k8sservice.html
netbox_k8s_manager/templates/netbox_k8s_manager/generic/bulk_remove.html
netbox_k8s_manager/templates/netbox_k8s_manager/viewtab_contact/k8scluster_contact.html
netbox_k8s_manager/views/__init__.py
netbox_k8s_manager/views/k8s_cluster.py
netbox_k8s_manager/views/k8s_cluster_type.py
netbox_k8s_manager/views/k8s_service.py
netbox_k8s_manager-1.0.0.dist-info/LICENSE
netbox_k8s_manager-1.0.0.dist-info/METADATA
netbox_k8s_manager-1.0.0.dist-info/WHEEL
netbox_k8s_manager-1.0.0.dist-info/top_level.txt
netbox_k8s_manager-1.0.0.dist-info/RECORD
