Metadata-Version: 2.1
Name: netbox-k8s-manager
Version: 1.0.0
Summary: K8s Manager Netbox Plugin
Author-email: ducna <ducna-hcd@gmail.com>
License: Apache-2.0
Classifier: Environment :: Web Environment
Classifier: Framework :: Django
Classifier: Intended Audience :: Developers
Classifier: License :: OSI Approved :: Apache Software License
Classifier: Operating System :: OS Independent
Classifier: Programming Language :: Python
Classifier: Programming Language :: Python :: 3
Classifier: Programming Language :: Python :: 3 :: Only
Classifier: Programming Language :: Python :: 3.11
Classifier: Programming Language :: Python :: 3.12
Classifier: Topic :: Internet :: WWW/HTTP
Classifier: Topic :: Internet :: WWW/HTTP :: Dynamic Content
Requires-Python: >=3.10.12
License-File: LICENSE
Provides-Extra: build
Requires-Dist: build==1.2.1; extra == "build"
Requires-Dist: setuptools==70.3.0; extra == "build"
Requires-Dist: twine==5.1.1; extra == "build"
Provides-Extra: tools
Requires-Dist: ruff==0.5.1; extra == "tools"
